urluna/__init__.py
urluna/flex.py
urluna/operator.py
urluna-1.6.dist-info/LICENSE
urluna-1.6.dist-info/METADATA
urluna-1.6.dist-info/WHEEL
urluna-1.6.dist-info/top_level.txt
urluna-1.6.dist-info/RECORD
