Metadata-Version: 2.1
Name: urluna
Version: 1.6
Summary: A flexible array operations library
Home-page: https://github.com/bursow/urluna
Author: Burhan
Author-email: burhan.sogutt@gmail.com
License: MIT
License-File: LICENSE
